django_nifty_attachments-0.1.1.dist-info/licenses/LICENSE
nifty_attachments/__init__.py
nifty_attachments/apps.py
nifty_attachments/forms.py
nifty_attachments/models.py
nifty_attachments/settings.py
nifty_attachments/urls.py
nifty_attachments/utils.py
nifty_attachments/validators.py
nifty_attachments/views.py
nifty_attachments/templates/nifty/attachments/add.html
nifty_attachments/templates/nifty/attachments/base.html
nifty_attachments/templates/nifty/attachments/list.html
nifty_attachments/templates/nifty/attachments/upload.html
nifty_attachments/templates/nifty/attachments/include/add_form.html
nifty_attachments/templates/nifty/attachments/include/attachment_list.html
nifty_attachments/templates/nifty/attachments/include/delete_link.html
nifty_attachments/templates/nifty/attachments/include/upload_form.html
nifty_attachments/templatetags/__init__.py
nifty_attachments/templatetags/attachments_tags.py
django_nifty_attachments-0.1.1.dist-info/METADATA
django_nifty_attachments-0.1.1.dist-info/WHEEL
django_nifty_attachments-0.1.1.dist-info/entry_points.txt
django_nifty_attachments-0.1.1.dist-info/top_level.txt
django_nifty_attachments-0.1.1.dist-info/RECORD
