Metadata-Version: 2.4
Name: django-nifty-attachments
Version: 0.1.1
Summary: A generic set of template tags to attach files to specific models.
Author-email: Joseph Fall <jfall@crgl.ca>
License: MIT License
Project-URL: Homepage, https://github.com/powderflask/django-nifty-attachments
Project-URL: Repository, https://github.com/powderflask/django-nifty-attachments
Keywords: nifty_attachments
Classifier: Development Status :: 2 - Pre-Alpha
Classifier: License :: OSI Approved :: MIT License
Classifier: Intended Audience :: Developers
Classifier: Natural Language :: English
Classifier: Programming Language :: Python :: 3
Classifier: Framework :: Django
Requires-Python: <4.0,>=3.10
License-File: LICENSE
Requires-Dist: django
Requires-Dist: factory_boy
Provides-Extra: format
Requires-Dist: black; extra == "format"
Requires-Dist: isort; extra == "format"
Provides-Extra: lint
Requires-Dist: flake8; extra == "lint"
Requires-Dist: flake8-bugbear; extra == "lint"
Provides-Extra: test
Requires-Dist: pytest; extra == "test"
Requires-Dist: pytest-django; extra == "test"
Requires-Dist: django_htmx; extra == "test"
Requires-Dist: pytest-sugar; extra == "test"
Requires-Dist: pytest-cov; extra == "test"
Provides-Extra: utils
Requires-Dist: tox; extra == "utils"
Requires-Dist: invoke; extra == "utils"
Requires-Dist: bumpver; extra == "utils"
Requires-Dist: pip-tools; extra == "utils"
Requires-Dist: build; extra == "utils"
Requires-Dist: twine; extra == "utils"
Dynamic: license-file
